stoobly/__init__.py
stoobly/api.py
stoobly/cli.py
stoobly/hot_reload.py
stoobly/proxy.py
stoobly/record.py
stoobly/app/configs_controller.py
stoobly/app/statuses_controller.py
stoobly/config/settings.yml
stoobly/config/settings.yml.sample
stoobly/lib/__init__.py
stoobly/lib/agent_api.py
stoobly/lib/cache.py
stoobly/lib/hashed_request_decorator.py
stoobly/lib/joined_request.py
stoobly/lib/logger.py
stoobly/lib/mitmproxy_request_adapter.py
stoobly/lib/mitmproxy_response_adapter.py
stoobly/lib/proxy_request.py
stoobly/lib/request.py
stoobly/lib/request_body_parser.py
stoobly/lib/request_string.py
stoobly/lib/response.py
stoobly/lib/response_string.py
stoobly/lib/scenarios_api.py
stoobly/lib/settings.py
stoobly/public/CHANGELOG.md
stoobly/public/README.md
stoobly/public/_redirects
stoobly/public/aliases-aliases-module-es2015.js
stoobly/public/aliases-aliases-module-es2015.js.map
stoobly/public/aliases-aliases-module-es5.js
stoobly/public/aliases-aliases-module-es5.js.map
stoobly/public/auth-pages-forgot-password-forgot-password-module-es2015.js
stoobly/public/auth-pages-forgot-password-forgot-password-module-es2015.js.map
stoobly/public/auth-pages-forgot-password-forgot-password-module-es5.js
stoobly/public/auth-pages-forgot-password-forgot-password-module-es5.js.map
stoobly/public/auth-pages-login-login-module-es2015.js
stoobly/public/auth-pages-login-login-module-es2015.js.map
stoobly/public/auth-pages-login-login-module-es5.js
stoobly/public/auth-pages-login-login-module-es5.js.map
stoobly/public/auth-pages-register-register-module-es2015.js
stoobly/public/auth-pages-register-register-module-es2015.js.map
stoobly/public/auth-pages-register-register-module-es5.js
stoobly/public/auth-pages-register-register-module-es5.js.map
stoobly/public/common-es2015.js
stoobly/public/common-es2015.js.map
stoobly/public/common-es5.js
stoobly/public/common-es5.js.map
stoobly-0.1.3.dist-info/LICENSE
stoobly-0.1.3.dist-info/METADATA
stoobly-0.1.3.dist-info/WHEEL
stoobly-0.1.3.dist-info/entry_points.txt
stoobly-0.1.3.dist-info/top_level.txt
stoobly-0.1.3.dist-info/RECORD
