Metadata-Version: 2.1
Name: stoobly
Version: 0.1.3
Summary: Client agent for Stoobly
Home-page: https://github.com/Stoobly/stoobly-agent
Author: Michael Yen
Author-email: michael@stoobly.com
License: MIT
Platform: UNKNOWN
Requires-Dist: click (<8.0.0,>=7.0.0)
Requires-Dist: mergedeep (<1.3.4,>=1.3.0)
Requires-Dist: mitmdump (<=1.1.2,>=1.1.0)
Requires-Dist: pyyaml (<=5.4.1,>=5.4)
Requires-Dist: requests (<=2.25.1,>=2.25.0)
Requires-Dist: watchdog (<=2.1.3,>=2.1.0)
